{
    "initial playcount": [
        42962,
        25796,
        36,
        715,
        948,
        1712,
        321,
        948,
        443,
        98,
        60951,
        12649,
        143,
        29,
        34,
        3,
        15295,
        960,
        83,
        20,
        8,
        15474,
        47024,
        4728,
        8903,
        32894,
        642,
        0,
        0,
        4,
        0,
        40,
        97,
        9,
        0,
        4,
        0
    ],
    "initial score": [
        55732467442,
        8280881296,
        3489701,
        148194188,
        212886808,
        799962182,
        69318981,
        114334922,
        35886575,
        13383152,
        42615700749,
        4939982088,
        24192940,
        5044202,
        13634954,
        212529,
        7472510434,
        366823139,
        8365956,
        1443820,
        0,
        22237678133,
        26716738329,
        2781833578,
        4861900896,
        9162291748,
        111988610,
        0,
        0,
        131176,
        0,
        1719860,
        12381314,
        686192,
        0,
        96800,
        0
    ],
    "level difficulty": "normal",
    "match name": "osu valley 2021-2022",
    "match score history": {
        "2021-11-29": {
            "BBenji": 3426174,
            "BirdPigeon": 2359903680,
            "CheeseDude": 6140192,
            "DiamondPVPr": 0,
            "Dukecj1": 0,
            "Forkk": 0,
            "GDcheerios": 11234702421,
            "Gman709": 12624157,
            "Golucky": 790741697,
            "GoodNightTokyo": 11205366,
            "Joe_Nuts69": 0,
            "KekumeSai": 0,
            "Kokuren": 15603985,
            "MargaritaMix08": 261036847,
            "Mcg_Tokyo": 0,
            "Mcg_mm8": 0,
            "Mexicutioner": 155060,
            "Minty_Fresch": 0,
            "Monvee": 117104,
            "Nyx Duke": 0,
            "Randomtangle": 128458,
            "Smol Glum": 19405328,
            "StarBoltZ": 0,
            "Trale_Lewous": 879180,
            "Trufflebuttt": 0,
            "Unknown User": 0,
            "UwU Aimi": 0,
            "Walterdoggg": 230829578,
            "aferchen": 1106611,
            "brianthe8east": 1298741,
            "casedama": 6499016235,
            "inferno_volt": 0,
            "peterparkermj": 162677,
            "pogo5512": 0,
            "st4rstrukk": 5112139818,
            "vinster19": 511089,
            "wildernesexplor": 1540695896
        },
        "2021-11-30": {
            "BBenji": 3426174,
            "BirdPigeon": 2359903680,
            "CheeseDude": 6140192,
            "DiamondPVPr": 0,
            "Dukecj1": 0,
            "Forkk": 0,
            "GDcheerios": 11297477998,
            "Gman709": 12624157,
            "Golucky": 797050875,
            "GoodNightTokyo": 11205366,
            "Joe_Nuts69": 0,
            "KekumeSai": 0,
            "Kokuren": 15603985,
            "MargaritaMix08": 261036847,
            "Mcg_Tokyo": 0,
            "Mcg_mm8": 0,
            "Mexicutioner": 155060,
            "Minty_Fresch": 0,
            "Monvee": 117104,
            "Nyx Duke": 0,
            "Randomtangle": 128458,
            "Smol Glum": 19405328,
            "StarBoltZ": 0,
            "Trale_Lewous": 879180,
            "Trufflebuttt": 0,
            "Unknown User": 0,
            "UwU Aimi": 0,
            "Walterdoggg": 230829578,
            "aferchen": 1106611,
            "brianthe8east": 1298741,
            "casedama": 6499016235,
            "inferno_volt": 0,
            "peterparkermj": 162677,
            "pogo5512": 0,
            "st4rstrukk": 5300198519,
            "vinster19": 511089,
            "wildernesexplor": 1542892613
        },
        "2021-12-01": {
            "BBenji": 3426174,
            "BirdPigeon": 2359903680,
            "CheeseDude": 6140192,
            "DiamondPVPr": 0,
            "Dukecj1": 0,
            "Forkk": 0,
            "GDcheerios": 11301684378,
            "Gman709": 12624157,
            "Golucky": 797050875,
            "GoodNightTokyo": 11205366,
            "Joe_Nuts69": 0,
            "KekumeSai": 0,
            "Kokuren": 15603985,
            "MargaritaMix08": 261036847,
            "Mcg_Tokyo": 0,
            "Mcg_mm8": 0,
            "Mexicutioner": 155060,
            "Minty_Fresch": 0,
            "Monvee": 117104,
            "Nyx Duke": 0,
            "Randomtangle": 128458,
            "Smol Glum": 19405328,
            "StarBoltZ": 0,
            "Trale_Lewous": 879180,
            "Trufflebuttt": 0,
            "Unknown User": 0,
            "UwU Aimi": 0,
            "Walterdoggg": 230829578,
            "aferchen": 1106611,
            "brianthe8east": 1298741,
            "casedama": 6499016235,
            "inferno_volt": 0,
            "peterparkermj": 162677,
            "pogo5512": 0,
            "st4rstrukk": 5300198519,
            "vinster19": 511089,
            "wildernesexplor": 1542892613
        },
        "2021-12-02": {
            "BBenji": 3426174,
            "BirdPigeon": 2359903680,
            "CheeseDude": 6140192,
            "DiamondPVPr": 0,
            "Dukecj1": 0,
            "Forkk": 0,
            "GDcheerios": 11379163321,
            "Gman709": 12624157,
            "Golucky": 797050875,
            "GoodNightTokyo": 11205366,
            "Joe_Nuts69": 0,
            "KekumeSai": 0,
            "Kokuren": 15603985,
            "MargaritaMix08": 261036847,
            "Mcg_Tokyo": 0,
            "Mcg_mm8": 0,
            "Mexicutioner": 155060,
            "Minty_Fresch": 0,
            "Monvee": 117104,
            "Nyx Duke": 0,
            "Randomtangle": 128458,
            "Smol Glum": 19405328,
            "StarBoltZ": 0,
            "Trale_Lewous": 879180,
            "Trufflebuttt": 0,
            "Unknown User": 0,
            "UwU Aimi": 0,
            "Walterdoggg": 230829578,
            "aferchen": 1106611,
            "brianthe8east": 1298741,
            "casedama": 6499016235,
            "inferno_volt": 0,
            "peterparkermj": 162677,
            "pogo5512": 0,
            "st4rstrukk": 5312961806,
            "vinster19": 511089,
            "wildernesexplor": 1542892613
        },
        "2021-12-07": {
            "BBenji": 3426174,
            "BirdPigeon": 2370181368,
            "CheeseDude": 6140192,
            "DiamondPVPr": 0,
            "Dukecj1": 0,
            "Forkk": 0,
            "GDcheerios": 11958545109,
            "Gman709": 12624157,
            "Golucky": 849128261,
            "GoodNightTokyo": 11205366,
            "Joe_Nuts69": 0,
            "KekumeSai": 0,
            "Kokuren": 16305467,
            "MargaritaMix08": 261036847,
            "Mcg_Tokyo": 0,
            "Mcg_mm8": 0,
            "Mexicutioner": 155060,
            "Minty_Fresch": 0,
            "Monvee": 117104,
            "Nyx Duke": 0,
            "Randomtangle": 128458,
            "Smol Glum": 19405328,
            "StarBoltZ": 0,
            "Trale_Lewous": 879180,
            "Trufflebuttt": 0,
            "Unknown User": 0,
            "UwU Aimi": 0,
            "Walterdoggg": 302893268,
            "aferchen": 2855569,
            "brianthe8east": 1298741,
            "casedama": 6908911537,
            "inferno_volt": 0,
            "peterparkermj": 162677,
            "pogo5512": 0,
            "st4rstrukk": 5663402678,
            "vinster19": 511089,
            "wildernesexplor": 1800264619
        },
        "2021-12-08": {
            "BBenji": 3426174,
            "BirdPigeon": 2370181368,
            "CheeseDude": 6140192,
            "DiamondPVPr": 0,
            "Dukecj1": 0,
            "Forkk": 0,
            "GDcheerios": 12017175565,
            "Gman709": 12624157,
            "Golucky": 849128261,
            "GoodNightTokyo": 11205366,
            "Joe_Nuts69": 0,
            "KekumeSai": 0,
            "Kokuren": 16305467,
            "MargaritaMix08": 261036847,
            "Mcg_Tokyo": 0,
            "Mcg_mm8": 0,
            "Mexicutioner": 155060,
            "Minty_Fresch": 0,
            "Monvee": 117104,
            "Nyx Duke": 0,
            "Randomtangle": 128458,
            "Smol Glum": 19405328,
            "StarBoltZ": 0,
            "Trale_Lewous": 879180,
            "Trufflebuttt": 0,
            "Unknown User": 0,
            "UwU Aimi": 0,
            "Walterdoggg": 302893268,
            "aferchen": 2855569,
            "brianthe8east": 1298741,
            "casedama": 6908911537,
            "inferno_volt": 0,
            "peterparkermj": 162677,
            "pogo5512": 0,
            "st4rstrukk": 5663402678,
            "vinster19": 511089,
            "wildernesexplor": 1800264619
        }
    },
    "mode": "ffa",
    "team metadata": {},
    "users": [
        "11339405",
        "17879839",
        "19160758",
        "17822521",
        "17965819",
        "18346314",
        "18993227",
        "16369108",
        "18037392",
        "17352685",
        "13789505",
        "17681245",
        "24499503",
        "24576716",
        "24650709",
        "24650798",
        "14670213",
        "20861610",
        "18355390",
        "20762152",
        "24036177",
        "WhiteToast",
        "13450060",
        "17090247",
        "17681359",
        "14506085",
        "17967231",
        "21475272",
        "17906393",
        "19252662",
        "21475233",
        "19999589",
        "21837210",
        "15027674",
        "25897425",
        "19266174",
        "27260180"
    ]
}